yt_playlist_updater.py
yt_playlist_updater-0.0.3.dist-info/METADATA
yt_playlist_updater-0.0.3.dist-info/WHEEL
yt_playlist_updater-0.0.3.dist-info/top_level.txt
yt_playlist_updater-0.0.3.dist-info/RECORD
